yapu/__about__.py
yapu/__init__.py
yapu/bash.py
yapu/dict.py
yapu/files.py
yapu/list.py
yapu/list_dict.py
yapu/multiline.py
yapu/seaborn.py
yapu/string.py
yapu/versioned_file.py
yapu/debug/__init__.py
yapu/debug/debug.py
yapu/debug/jupyter.py
yapu/debug/profile.py
yapu/debug/trace.py
yapu/imports/__init__.py
yapu/imports/all.py
yapu/imports/external.py
yapu/imports/internal.py
yapu/imports/stdlib.py
yapu/meta/__init__.py
yapu/meta/decorator.py
yapu/meta/listify.py
yapu/meta/meta.py
yapu-1.0.0-py3.6.egg-info/PKG-INFO
yapu-1.0.0-py3.6.egg-info/SOURCES.txt
yapu-1.0.0-py3.6.egg-info/dependency_links.txt
yapu-1.0.0-py3.6.egg-info/top_level.txt
yapu-1.0.0.dist-info/dependency_links.txt
yapu-1.0.0.dist-info/top_level.txt
yapu-1.0.1.dist-info/LICENSE
yapu-1.0.1.dist-info/METADATA
yapu-1.0.1.dist-info/WHEEL
yapu-1.0.1.dist-info/top_level.txt
yapu-1.0.1.dist-info/RECORD
